Workbook

Sheet Leia-me
A1: Jardines de Cenizas — Estimativa de custos dos novos produtos
A2: Base: projeto paisagístico de Luana Magedanz (Canva “Jardines de Cenizas”, 2026) + portfólio “Nuevos Productos y Servicios · VANGRUPO”.
A3: Moeda: USD. Custos de compra estimados para El Salvador (mercado dolarizado), com IVA 13% embutido, valores de referência out/2026.
A5: DOIS CENÁRIOS (aba Cenários)
A6: • Cenário B — Só produto: custo direto de cada unidade vendida (cova, urna, contenedor, placa, instalação, cerimônia).
A7: • Cenário A — Produto + obra: custo direto + rateio do investimento de obra do jardim (caminho, nivelamento, bordillo, paisagismo, água, bancos…).
A8: Rateio = Obra do jardim × % alocada ao produto ÷ unidades de rateio × posições que a unidade ocupa.
A9: Unidades de rateio = capacidade do jardim × % da capacidade usada para amortizar (premissa — padrão 70%, ou seja, a obra se paga antes de lotar).
A11: COMO EDITAR
A12: • Texto AZUL = premissa/entrada editável. Fundo AMARELO = premissa-chave que deve ser validada com a VANGRUPO / fornecedores locais.
A13: • Texto PRETO = fórmula (não editar). Texto VERDE = vínculo com outra aba.
A14: • Ordem sugerida: 1) Premissas (áreas, comprimentos de caminho, capacidade de cada jardim) 2) Custos Unitários (cotações reais) 3) conferir Cenários.
... A21: • Preço sugerido = custo ÷ (1 − comissão − fundo de manutenção − adm/marketing − margem alvo), depois + IVA. Percentuais editáveis em Premissas.

Sheet Cenários
A1: Cenários de custo e parâmetro de preço por produto
A2: Cenário B = só produto | Cenário A = produto + rateio da obra. Preço sugerido = custo ÷ (1 − comissão − fundo manutenção − adm/mkt − margem alvo); valores com IVA para comparação com o deck VANGRUPO.
A4: Produto | B4: Jardim | C4: Linha (deck) | D4: Custo direto Cenário B | E4: Obra do jardim | F4: % obra alocada | G4: Base de rateio (un.) | H4: Posições por unidade | I4: Rateio obra / unidade | K4: Custo total Cenário A | L4: Preço sugerido B (c/ IVA) | M4: Preço sugerido A (c/ IVA) | N4: Preço s/ IVA A | P4: Deck – preço mín. | Q4: Deck – preço máx. | R4: Margem líquida A no preço mín. do deck | S4: Margem líquida A no preço máx. do deck
A5: Ecológico – placa de madeira | B5: Curva 1 – Subida (Ecológico) | C5: Standard | D5: =Produtos!D$23 -> 51 | E5: =Obra!J$23 -> 13204.2 | F5: 1 | G5: =Premissas!$C$21*Premissas!$C$6 -> 140 | H5: 1 | I5: =IFERROR(E5*F5/G5*H5,0) -> 94.315714 | K5: =D5+I5 -> 145.31571 | L5: =D5/(1-Premissas!$C$9-Premissas!$C$10-Premissas!$C$11-Premissas!$C$12)*(1+Premissas!$C$13) -> 137.21429 | M5: =K5/(1-Premissas!$C$9-Premissas!$C$10-Premissas!$C$11-Premissas!$C$12)*(1+Premissas!$C$13) -> 390.96847 | N5: =K5/(1-Premissas!$C$9-Premissas!$C$10-Premissas!$C$11-Premissas!$C$12) -> 345.9898 | P5: 400 | Q5: 600 | R5: =IFERROR(1-K5/(P5/(1+Premissas!$C$13))-(Premissas!$C$9+Premissas!$C$10+Premissas!$C$11),0) -> 0.30948311 | S5: =IFERROR(1-K5/(Q5/(1+Premissas!$C$13))-(Premissas!$C$9+Premissas!$C$10+Premissas!$C$11),0) -> 0.44632207
A6: Ecológico – placa em varilla | B6: Jardín 2 – Ecológico + Aspersión | C6: Standard | D6: =Produtos!E$23 -> 56 | E6: =Obra!L$23 -> 32379.2 | F6: =1-Premissas!$C$8 -> 0.7 | G6: =Premissas!$E$21*Premissas!$C$6 -> 210 | H6: 1 | I6: =IFERROR(E6*F6/G6*H6,0) -> 107.93067 | K6: =D6+I6 -> 163.93067 | L6: =D6/(1-Premissas!$C$9-Premissas!$C$10-Premissas!$C$11-Premissas!$C$12)*(1+Premissas!$C$13) -> 150.66667 | M6: =K6/(1-Premissas!$C$9-Premissas!$C$10-Premissas!$C$11-Premissas!$C$12)*(1+Premissas!$C$13) -> 441.05156 | N6: =K6/(1-Premissas!$C$9-Premissas!$C$10-Premissas!$C$11-Premissas!$C$12) -> 390.31111 | P6: 400 | Q6: 600 | R6: =IFERROR(1-K6/(P6/(1+Premissas!$C$13))-(Premissas!$C$9+Premissas!$C$10+Premissas!$C$11),0) -> 0.25689587 | S6: =IFERROR(1-K6/(Q6/(1+Premissas!$C$13))-(Premissas!$C$9+Premissas!$C$10+Premissas!$C$11),0) -> 0.41126391
A7: Bosque Orquídeas – placa mármore | B7: Jardín 2 – Bosque de las Orquídeas | C7: Standard | D7: =Produtos!F$23 -> 77 | E7: =Obra!M$23 -> 14169.44 | F7: 1 | G7: =Premissas!$F$21*Premissas!$C$6 -> 140 | H7: 1 | I7: =IFERROR(E7*F7/G7*H7,0) -> 101.21029 | K7: =D7+I7 -> 178.21029 | L7: =D7/(1-Premissas!$C$9-Premissas!$C$10-Premissas!$C$11-Premissas!$C$12)*(1+Premissas!$C$13) -> 207.16667 | M7: =K7/(1-Premissas!$C$9-Premissas!$C$10-Premissas!$C$11-Premissas!$C$12)*(1+Premissas!$C$13) -> 479.47053 | N7: =K7/(1-Premissas!$C$9-Premissas!$C$10-Premissas!$C$11-Premissas!$C$12) -> 424.3102 | P7: 400 | Q7: 600 | R7: =IFERROR(1-K7/(P7/(1+Premissas!$C$13))-(Premissas!$C$9+Premissas!$C$10+Premissas!$C$11),0) -> 0.21655594 | S7: =IFERROR(1-K7/(Q7/(1+Premissas!$C$13))-(Premissas!$C$9+Premissas!$C$10+Premissas!$C$11),0) -> 0.38437063
A8: Urna c/ contenedor + tampa granito | B8: Jardín 1 – Urnas | C8: Standard | D8: =Produtos!G$23 -> 95 | E8: =Obra!K$23 -> 18837.52 | F8: 1 | G8: =Premissas!$D$21*Premissas!$C$6 -> 210 | H8: 1 | I8: =IFERROR(E8*F8/G8*H8,0) -> 89.702476 | K8: =D8+I8 -> 184.70248 | L8: =D8/(1-Premissas!$C$9-Premissas!$C$10-Premissas!$C$11-Premissas!$C$12)*(1+Premissas!$C$13) -> 255.59524 | M8: =K8/(1-Premissas!$C$9-Premissas!$C$10-Premissas!$C$11-Premissas!$C$12)*(1+Premissas!$C$13) -> 496.93761 | N8: =K8/(1-Premissas!$C$9-Premissas!$C$10-Premissas!$C$11-Premissas!$C$12) -> 439.7678 | P8: 400 | Q8: 600 | R8: =IFERROR(1-K8/(P8/(1+Premissas!$C$13))-(Premissas!$C$9+Premissas!$C$10+Premissas!$C$11),0) -> 0.1982155 | S8: =IFERROR(1-K8/(Q8/(1+Premissas!$C$13))-(Premissas!$C$9+Premissas!$C$10+Premissas!$C$11),0) -> 0.37214367
A9: Ceremonial – cilindro concreto + mármore | B9: Jardín 3 – Ceremonial | C9: Standard | D9: =Produtos!H$23 -> 93 | E9: =Obra!N$23 -> 18844.6 | F9: 1 | G9: =Premissas!$G$21*Premissas!$C$6 -> 105 | H9: 1 | I9: =IFERROR(E9*F9/G9*H9,0) -> 179.47238 | K9: =D9+I9 -> 272.47238 | L9: =D9/(1-Premissas!$C$9-Premissas!$C$10-Premissas!$C$11-Premissas!$C$12)*(1+Premissas!$C$13) -> 250.21429 | M9: =K9/(1-Premissas!$C$9-Premissas!$C$10-Premissas!$C$11-Premissas!$C$12)*(1+Premissas!$C$13) -> 733.08045 | N9: =K9/(1-Premissas!$C$9-Premissas!$C$10-Premissas!$C$11-Premissas!$C$12) -> 648.74376 | P9: 400 | Q9: 600 | R9: =IFERROR(1-K9/(P9/(1+Premissas!$C$13))-(Premissas!$C$9+Premissas!$C$10+Premissas!$C$11),0) -> -0.049734476 | S9: =IFERROR(1-K9/(Q9/(1+Premissas!$C$13))-(Premissas!$C$9+Premissas!$C$10+Premissas!$C$11),0) -> 0.20684368
A10: Premium familiar (4 posições) | B10: Jardín 1 – Urnas | C10: Premium | D10: =Produtos!I$23 -> 462 | E10: =Obra!K$23 -> 18837.52 | F10: 1 | G10: =Premissas!$D$21*Premissas!$C$6 -> 210 | H10: 4 | I10: =IFERROR(E10*F10/G10*H10,0) -> 358.8099 | K10: =D10+I10 -> 820.8099 | L10: =D10/(1-Premissas!$C$9-Premissas!$C$10-Premissas!$C$11-Premissas!$C$12)*(1+Premissas!$C$13) -> 1243 | M10: =K10/(1-Premissas!$C$9-Premissas!$C$10-Premissas!$C$11-Premissas!$C$12)*(1+Premissas!$C$13) -> 2208.3695 | N10: =K10/(1-Premissas!$C$9-Premissas!$C$10-Premissas!$C$11-Premissas!$C$12) -> 1954.3093 | P10: 1490 | Q10: 1990 | R10: =IFERROR(1-K10/(P10/(1+Premissas!$C$13))-(Premissas!$C$9+Premissas!$C$10+Premissas!$C$11),0) -> 0.097506582 | S10: =IFERROR(1-K10/(Q10/(1+Premissas!$C$13))-(Premissas!$C$9+Premissas!$C$10+Premissas!$C$11),0) -> 0.25391196
A11: Ritual de aspersão de cinzas | B11: Jardín 2 – Ecológico + Aspersión | C11: Aspersión | D11: =Produtos!J$23 -> 48 | E11: =Obra!L$23 -> 32379.2 | F11: =Premissas!$C$8 -> 0.3 | G11: =Premissas!$C$7 -> 300 | H11: 1 | I11: =IFERROR(E11*F11/G11*H11,0) -> 32.3792 | K11: =D11+I11 -> 80.3792 | L11: =D11/(1-Premissas!$C$9-Premissas!$C$10-Premissas!$C$11-Premissas!$C$12)*(1+Premissas!$C$13) -> 129.14286 | M11: =K11/(1-Premissas!$C$9-Premissas!$C$10-Premissas!$C$11-Premissas!$C$12)*(1+Premissas!$C$13) -> 216.25832 | N11: =K11/(1-Premissas!$C$9-Premissas!$C$10-Premissas!$C$11-Premissas!$C$12) -> 191.37905 | P11: 150 | Q11: 250 | R11: =IFERROR(1-K11/(P11/(1+Premissas!$C$13))-(Premissas!$C$9+Premissas!$C$10+Premissas!$C$11),0) -> 0.11447669 | S11: =IFERROR(1-K11/(Q11/(1+Premissas!$C$13))-(Premissas!$C$9+Premissas!$C$10+Premissas!$C$11),0) -> 0.35668602
A13: Resumo do investimento
A14: Indicador | D14: Valor
A15: Investimento total de obra (5 jardins, c/ adm. e contingência) | D15: =Obra!O23 -> 97434.96
A16: Capacidade total (posições) | D16: =Obra!O25 -> 1150
A17: Obra média por posição (amortizando em % da capacidade) | D17: =Obra!O27 -> 121.03722
A18: Margem alvo usada no preço sugerido | D18: =Premissas!$C$12 -> 0.3
A19: Custos variáveis sobre preço (comissão + fundo + adm/mkt) | D19: =Premissas!$C$9+Premissas!$C$10+Premissas!$C$11 -> 0.28
A21: Leitura: margem líquida negativa ou abaixo da margem alvo indica que a faixa de preço do deck não cobre custo + obra + variáveis — revisar preço, composição ou capacidade.

Sheet Premissas
A1: Premissas gerais e dos jardins
A3: Premissa geral | B3: Unid. | C3: Valor | H3: Nota / fonte
A4: Contingência sobre obra | B4: % | C4: 0.1 | H4: Imprevistos de obra; padrão de mercado 10%.
A5: Administração / gestão de obra | B5: % | C5: 0.08 | H5: Encarregado, ferramentas, fretes, canteiro.
A6: % da capacidade usada para amortizar a obra | B6: % | C6: 0.7 | H6: Obra é paga pelos primeiros 70% de lotes vendidos (conservador).
A7: Nº de cerimônias de aspersão no horizonte de amortização | B7: un | C7: 300 | H7: Ex.: 5 anos × 60 cerimônias/ano. Validar com histórico de cremações.
A8: % da obra do Jardín 2 Ecológico alocada à aspersão | B8: % | C8: 0.3 | H8: Área de esparcimiento + água corrente compartilhadas com lotes ecológicos.
A9: Comissão de vendas | B9: % preço | C9: 0.1 | H9: Sobre preço sem IVA.
A10: Fundo de manutenção perpétua | B10: % preço | C10: 0.1 | H10: Reserva para manter jardim, poda, irrigação, reposição de placas.
A11: Despesas adm./marketing | B11: % preço | C11: 0.08 | H11: Lançamento Día de los Muertos, material, atendimento.
A12: Margem alvo (lucro) | B12: % preço | C12: 0.3 | H12: Margem líquida desejada sobre preço sem IVA.
A13: IVA El Salvador | B13: % | C13: 0.13 | H13: Imposto al Valor Agregado (13%).
A15: Premissas por jardim (substituir pela planta / levantamento)
A16: Parâmetro | B16: Unid. | C16: Curva 1 – Subida (Ecológico) | D16: Jardín 1 – Urnas | E16: Jardín 2 – Ecológico + Aspersión | F16: Jardín 2 – Bosque de las Orquídeas | G16: Jardín 3 – Ceremonial | H16: Nota
A17: Área total de intervenção | B17: m² | C17: 300 | D17: 600 | E17: 800 | F17: 500 | G17: 400 | H17: Estimada a partir das fotos; medir em campo.
A18: Comprimento do caminho / vía peatonal | B18: m | C18: 60 | D18: 80 | E18: 100 | F18: 60 | G18: 50 | H18: Canva: caminho 1,2 m em gravilla com bordillo prefabricado; Curva 1: vía peatonal ≥1 m junto ao bordillo.
A19: Largura do caminho | B19: m | C19: 1 | D19: 1.2 | E19: 1.2 | F19: 1.2 | G19: 1.2 | H19: Conforme Canva.
A20: Área de paisagismo (plantio) | B20: m² | C20: 200 | D20: 400 | E20: 500 | F20: 250 | G20: 250 | H20: Plantas de sombra, alturas e texturas variadas.
A21: Capacidade (posições de inumação) | B21: posições | C21: 200 | D21: 300 | E21: 300 | F21: 200 | G21: 150 | H21: Cova 30×30×40 cm; ~0,5 m² por posição com circulação.
A23: Fontes: projeto Canva “Jardines de Cenizas” (Luana Magedanz); dimensões não informadas no projeto são estimativas.

Sheet Custos Unitários
A1: Custos unitários de referência (USD, com IVA, El Salvador)
A3: ID | B3: Item | C3: Unid. | D3: Custo unit. (US$) | E3: Premissa / fonte
A4: OBRA
A5: O1 | B5: Topografia, locação e traçado do caminho | C5: vb | D5: 350 | E5: Levantamento simples + marcação. Canva: “trazar primero el camino”.
A6: O2 | B6: Limpeza, destoca leve e nivelamento do terreno | C6: m² | D6: 3.5 | E6: Mão de obra + roçada + regularização manual/mini-carregadeira.
A7: O3 | B7: Caminho em gravilla (escavação 10 cm, geotêxtil, base compactada, gravilla 8 cm) | C7: m² | D7: 14 | E7: Gravilla ≈ US$51/m³ (El Mundo SV, jul/2026) + geotêxtil + base + MO.
A8: O4 | B8: Bordillo prefabricado de concreto (fornec. + assentamento) | C8: ml | D8: 11 | E8: Peça pré-moldada de jardim + argamassa + MO. Aplicado nos 2 lados do caminho.
A9: O5 | B9: Vía peatonal em concreto 8 cm (aclive – Curva 1) | C9: m² | D9: 32 | E9: No aclive, gravilla escorre; concreto é mais adequado. Canva: ≥1 m junto ao bordillo.
A10: O6 | B10: Terraços / contenção com troncos tratados | C10: ml | D10: 18 | E10: Referência foto Curva 1 (degraus com troncos).
A11: O7 | B11: Terra vegetal + adubação + mulch | C11: m² | D11: 4 | E11: 10 cm de terra preparada nas áreas de plantio.
A12: O8 | B12: Plantas de sombra (mudas, plantio) | C12: m² | D12: 16 | E12: Mix de folhagens/arbustos de sombra, ~4 mudas/m².
A13: O9 | B13: Orquídeas fixadas em árvores | C13: un | D13: 10 | E13: Bosque de las Orquídeas.
A14: O10 | B14: Irrigação básica (gotejo/mangueira) | C14: m² | D14: 3 | E14: Sobre área de paisagismo.
A15: O11 | B15: Banco contemplativo (concreto/madeira) | C15: un | D15: 380 | E15: Canva Jardín 1: “dejar espacio para un banco”.
A16: O12 | B16: Água corrente / riacho recirculante (liner, pedras, bomba) | C16: vb | D16: 6500 | E16: Canva Jardín 2: agua corriente que se extiende hasta el jardín.
... A20: O16 | B20: Totem / sinalização de identificação do jardim | C20: un | D20: 450 | E20: Placa de entrada + regras de uso.
A21: PRODUTO
A22: P1 | B22: Abertura e fechamento de cova 30×30×40 cm (MO) | C22: un | D22: 4 | E22: ~30 min de ajudante, incl. encargos.
A23: P2 | B23: Urna ecológica biodegradável (juta/papelão/sal) | C23: un | D23: 22 | E23: Canva: urnas ecológicas (saco de juta / caixa kraft). Preço atacado.
A24: P3 | B24: Placa de madeira Ø20 cm tratada (autoclave) + gravação laser | C24: un | D24: 14 | E24: Canva: verificar tratamento para não deteriorar em contato com o solo.
A25: P4 | B25: Estaca de fixação da placa de madeira | C25: un | D25: 2
A26: P5 | B26: Varilla metálica galvanizada para placa vertical | C26: un | D26: 7 | E26: Canva Jardín 2: placas em varilla, sem contato com o solo.
A27: P6 | B27: Placa de mármore 20×15 cm gravada | C27: un | D27: 38 | E27: Canva Bosque / Jardín 3.
A28: P7 | B28: Contenedor cilíndrico Ø32×40 cm (polietileno) | C28: un | D28: 32 | E28: Canva Jardín 1: enterrar deixando 20 cm à vista.
A29: P8 | B29: Tampa de granito Ø32 cm (corte + polimento) | C29: un | D29: 30 | E29: Canva: “se sustituye la tapa por una tapa de granito”.
A30: P9 | B30: Placa vidro/policarbonato 15×10 cm gravada + fixação | C30: un | D30: 16 | E30: Canva Jardín 1.
A31: P10 | B31: Cilindro pré-moldado de concreto c/ tampa | C31: un | D31: 38 | E31: Canva pág. 9 (Jardín para inhumación de urnas).
A32: P11 | B32: Base drenante (gravilla/areia) por cova | C32: un | D32: 2 | E32: ≈0,02 m³ por cova.
A33: P12 | B33: Mão de obra de instalação (contenedor/placa) | C33: un | D33: 8 | E33: Assentamento, nível, rejunte.
A34: P13 | B34: Planta individual de homenagem | C34: un | D34: 6 | E34: Muda plantada junto à placa.
A35: P14 | B35: Placa familiar de granito 40×30 cm gravada (Premium) | C35: un | D35: 95 | E35: Acabamento de linha superior (deck VANGRUPO).
A36: P15 | B36: Paisagismo exclusivo do lote familiar (Premium) | C36: un | D36: 60 | E36: Bordadura + plantas diferenciadas.
A37: P16 | B37: Pétalas/flores para cerimônia | C37: un | D37: 15 | E37: Aspersión.
... A40: P19 | B40: Registro, certificado e documentação | C40: un | D40: 3 | E40: Impressão + controle de localização.
B42: Fonte gravilla/areia: diario.elmundo.sv – “Asfalto, cemento, bloques y otros materiales reportan incrementos” (2026). Demais: referências de mercado, validar com cotações locais.

Sheet Obra
A1: Investimento de obra por jardim (Cenário A)
D2: Quantidades | J2: Custo
A3: Item | B3: Unid. | C3: Custo unit. | D3: Curva 1 qtd. | E3: Jardín 1 qtd. | F3: Jardín 2 qtd. | G3: Jardín 2 qtd. | H3: Jardín 3 qtd. | J3: Curva 1 US$ | K3: Jardín 1 US$ | L3: Jardín 2 US$ | M3: Jardín 2 US$ | N3: Jardín 3 US$ | O3: Total US$
A4: Topografia, locação e traçado do caminho | B4: vb | C4: ='Custos Unitários'!$D$5 -> 350 | D4: 1 | E4: 1 | F4: 1 | G4: 1 | H4: 1 | J4: =$C4*D4 -> 350 | K4: =$C4*E4 -> 350 | L4: =$C4*F4 -> 350 | M4: =$C4*G4 -> 350 | N4: =$C4*H4 -> 350 | O4: =SUM(J4:N4) -> 1750
A5: Limpeza, destoca leve e nivelamento do terreno | B5: m² | C5: ='Custos Unitários'!$D$6 -> 3.5 | D5: =Premissas!$C$17 -> 300 | E5: =Premissas!$D$17 -> 600 | F5: =Premissas!$E$17 -> 800 | G5: =Premissas!$F$17 -> 500 | H5: =Premissas!$G$17 -> 400 | J5: =$C5*D5 -> 1050 | K5: =$C5*E5 -> 2100 | L5: =$C5*F5 -> 2800 | M5: =$C5*G5 -> 1750 | N5: =$C5*H5 -> 1400 | O5: =SUM(J5:N5) -> 9100
A6: Caminho em gravilla (escavação 10 cm, geotêxtil, base compactada, gravilla 8 cm) | B6: m² | C6: ='Custos Unitários'!$D$7 -> 14 | D6: 0 | E6: =Premissas!$D$18*Premissas!$D$19 -> 96 | F6: =Premissas!$E$18*Premissas!$E$19 -> 120 | G6: =Premissas!$F$18*Premissas!$F$19 -> 72 | H6: =Premissas!$G$18*Premissas!$G$19 -> 60 | J6: =$C6*D6 -> 0 | K6: =$C6*E6 -> 1344 | L6: =$C6*F6 -> 1680 | M6: =$C6*G6 -> 1008 | N6: =$C6*H6 -> 840 | O6: =SUM(J6:N6) -> 4872
A7: Bordillo prefabricado de concreto (fornec. + assentamento) | B7: ml | C7: ='Custos Unitários'!$D$8 -> 11 | D7: =Premissas!$C$18 -> 60 | E7: =2*Premissas!$D$18 -> 160 | F7: =2*Premissas!$E$18 -> 200 | G7: =2*Premissas!$F$18 -> 120 | H7: =2*Premissas!$G$18 -> 100 | J7: =$C7*D7 -> 660 | K7: =$C7*E7 -> 1760 | L7: =$C7*F7 -> 2200 | M7: =$C7*G7 -> 1320 | N7: =$C7*H7 -> 1100 | O7: =SUM(J7:N7) -> 7040
A8: Vía peatonal em concreto 8 cm (aclive – Curva 1) | B8: m² | C8: ='Custos Unitários'!$D$9 -> 32 | D8: =Premissas!$C$18*Premissas!$C$19 -> 60 | E8: 0 | F8: 0 | G8: 0 | H8: 0 | J8: =$C8*D8 -> 1920 | K8: =$C8*E8 -> 0 | L8: =$C8*F8 -> 0 | M8: =$C8*G8 -> 0 | N8: =$C8*H8 -> 0 | O8: =SUM(J8:N8) -> 1920
A9: Terraços / contenção com troncos tratados | B9: ml | C9: ='Custos Unitários'!$D$10 -> 18 | D9: 120 | E9: 0 | F9: 0 | G9: 0 | H9: 0 | J9: =$C9*D9 -> 2160 | K9: =$C9*E9 -> 0 | L9: =$C9*F9 -> 0 | M9: =$C9*G9 -> 0 | N9: =$C9*H9 -> 0 | O9: =SUM(J9:N9) -> 2160
A10: Terra vegetal + adubação + mulch | B10: m² | C10: ='Custos Unitários'!$D$11 -> 4 | D10: =Premissas!$C$20 -> 200 | E10: =Premissas!$D$20 -> 400 | F10: =Premissas!$E$20 -> 500 | G10: =Premissas!$F$20 -> 250 | H10: =Premissas!$G$20 -> 250 | J10: =$C10*D10 -> 800 | K10: =$C10*E10 -> 1600 | L10: =$C10*F10 -> 2000 | M10: =$C10*G10 -> 1000 | N10: =$C10*H10 -> 1000 | O10: =SUM(J10:N10) -> 6400
A11: Plantas de sombra (mudas, plantio) | B11: m² | C11: ='Custos Unitários'!$D$12 -> 16 | D11: =Premissas!$C$20 -> 200 | E11: =Premissas!$D$20 -> 400 | F11: =Premissas!$E$20 -> 500 | G11: =Premissas!$F$20 -> 250 | H11: =Premissas!$G$20 -> 250 | J11: =$C11*D11 -> 3200 | K11: =$C11*E11 -> 6400 | L11: =$C11*F11 -> 8000 | M11: =$C11*G11 -> 4000 | N11: =$C11*H11 -> 4000 | O11: =SUM(J11:N11) -> 25600
A12: Orquídeas fixadas em árvores | B12: un | C12: ='Custos Unitários'!$D$13 -> 10 | D12: 0 | E12: 0 | F12: 0 | G12: 100 | H12: 0 | J12: =$C12*D12 -> 0 | K12: =$C12*E12 -> 0 | L12: =$C12*F12 -> 0 | M12: =$C12*G12 -> 1000 | N12: =$C12*H12 -> 0 | O12: =SUM(J12:N12) -> 1000
A13: Irrigação básica (gotejo/mangueira) | B13: m² | C13: ='Custos Unitários'!$D$14 -> 3 | D13: =Premissas!$C$20 -> 200 | E13: =Premissas!$D$20 -> 400 | F13: =Premissas!$E$20 -> 500 | G13: =Premissas!$F$20 -> 250 | H13: =Premissas!$G$20 -> 250 | J13: =$C13*D13 -> 600 | K13: =$C13*E13 -> 1200 | L13: =$C13*F13 -> 1500 | M13: =$C13*G13 -> 750 | N13: =$C13*H13 -> 750 | O13: =SUM(J13:N13) -> 4800
A14: Banco contemplativo (concreto/madeira) | B14: un | C14: ='Custos Unitários'!$D$15 -> 380 | D14: 0 | E14: 2 | F14: 2 | G14: 1 | H14: 2 | J14: =$C14*D14 -> 0 | K14: =$C14*E14 -> 760 | L14: =$C14*F14 -> 760 | M14: =$C14*G14 -> 380 | N14: =$C14*H14 -> 760 | O14: =SUM(J14:N14) -> 2660
A15: Água corrente / riacho recirculante (liner, pedras, bomba) | B15: vb | C15: ='Custos Unitários'!$D$16 -> 6500 | D15: 0 | E15: 0 | F15: 1 | G15: 0 | H15: 0 | J15: =$C15*D15 -> 0 | K15: =$C15*E15 -> 0 | L15: =$C15*F15 -> 6500 | M15: =$C15*G15 -> 0 | N15: =$C15*H15 -> 0 | O15: =SUM(J15:N15) -> 6500
A16: Fonte cerimonial pré-fabricada + bomba | B16: vb | C16: ='Custos Unitários'!$D$17 -> 3000 | D16: 0 | E16: 0 | F16: 0 | G16: 0 | H16: 1 | J16: =$C16*D16 -> 0 | K16: =$C16*E16 -> 0 | L16: =$C16*F16 -> 0 | M16: =$C16*G16 -> 0 | N16: =$C16*H16 -> 3000 | O16: =SUM(J16:N16) -> 3000
A17: Instalação elétrica/hidráulica para bombas | B17: vb | C17: ='Custos Unitários'!$D$18 -> 1200 | D17: 0 | E17: 0 | F17: 1 | G17: 0 | H17: 1 | J17: =$C17*D17 -> 0 | K17: =$C17*E17 -> 0 | L17: =$C17*F17 -> 1200 | M17: =$C17*G17 -> 0 | N17: =$C17*H17 -> 1200 | O17: =SUM(J17:N17) -> 2400
A18: Barreira visual (cerca viva / biombo vegetal) | B18: ml | C18: ='Custos Unitários'!$D$19 -> 28 | D18: 0 | E18: 0 | F18: 0 | G18: 0 | H18: 40 | J18: =$C18*D18 -> 0 | K18: =$C18*E18 -> 0 | L18: =$C18*F18 -> 0 | M18: =$C18*G18 -> 0 | N18: =$C18*H18 -> 1120 | O18: =SUM(J18:N18) -> 1120
A19: Totem / sinalização de identificação do jardim | B19: un | C19: ='Custos Unitários'!$D$20 -> 450 | D19: 1 | E19: 1 | F19: 1 | G19: 1 | H19: 1 | J19: =$C19*D19 -> 450 | K19: =$C19*E19 -> 450 | L19: =$C19*F19 -> 450 | M19: =$C19*G19 -> 450 | N19: =$C19*H19 -> 450 | O19: =SUM(J19:N19) -> 2250
A20: Subtotal obra direta | J20: =SUM(J4:J19) -> 11190 | K20: =SUM(K4:K19) -> 15964 | L20: =SUM(L4:L19) -> 27440 | M20: =SUM(M4:M19) -> 12008 | N20: =SUM(N4:N19) -> 15970 | O20: =SUM(J20:N20) -> 82572
A21: Administração / gestão de obra | J21: =J20*Premissas!$C$5 -> 895.2 | K21: =K20*Premissas!$C$5 -> 1277.12 | L21: =L20*Premissas!$C$5 -> 2195.2 | M21: =M20*Premissas!$C$5 -> 960.64 | N21: =N20*Premissas!$C$5 -> 1277.6 | O21: =SUM(J21:N21) -> 6605.76
A22: Contingência | J22: =J20*Premissas!$C$4 -> 1119 | K22: =K20*Premissas!$C$4 -> 1596.4 | L22: =L20*Premissas!$C$4 -> 2744 | M22: =M20*Premissas!$C$4 -> 1200.8 | N22: =N20*Premissas!$C$4 -> 1597 | O22: =SUM(J22:N22) -> 8257.2
A23: TOTAL INVESTIMENTO DE OBRA | J23: =J20+J21+J22 -> 13204.2 | K23: =K20+K21+K22 -> 18837.52 | L23: =L20+L21+L22 -> 32379.2 | M23: =M20+M21+M22 -> 14169.44 | N23: =N20+N21+N22 -> 18844.6 | O23: =SUM(J23:N23) -> 97434.96
A25: Capacidade (posições) | J25: =Premissas!$C$21 -> 200 | K25: =Premissas!$D$21 -> 300 | L25: =Premissas!$E$21 -> 300 | M25: =Premissas!$F$21 -> 200 | N25: =Premissas!$G$21 -> 150 | O25: =SUM(J25:N25) -> 1150
A26: Obra por posição (capacidade total) | J26: =IFERROR(J23/J25,0) -> 66.021 | K26: =IFERROR(K23/K25,0) -> 62.791733 | L26: =IFERROR(L23/L25,0) -> 107.93067 | M26: =IFERROR(M23/M25,0) -> 70.8472 | N26: =IFERROR(N23/N25,0) -> 125.63067 | O26: =IFERROR(O23/O25,0) -> 84.726052
A27: Obra por posição (amortizando em % da capacidade) | J27: =IFERROR(J23/(J25*Premissas!$C$6),0) -> 94.315714 | K27: =IFERROR(K23/(K25*Premissas!$C$6),0) -> 89.702476 | L27: =IFERROR(L23/(L25*Premissas!$C$6),0) -> 154.18667 | M27: =IFERROR(M23/(M25*Premissas!$C$6),0) -> 101.21029 | N27: =IFERROR(N23/(N25*Premissas!$C$6),0) -> 179.47238 | O27: =IFERROR(O23/(O25*Premissas!$C$6),0) -> 121.03722

Sheet Produtos
A1: Composição de custo direto por produto (Cenário B)
A3: Item | B3: Unid. | C3: Custo unit. | D3: Ecológico – placa de madeira | E3: Ecológico – placa em varilla | F3: Bosque Orquídeas – placa mármore | G3: Urna c/ contenedor + tampa granito | H3: Ceremonial – cilindro concreto + mármore | I3: Premium familiar (4 posições) | J3: Ritual de aspersão de cinzas
A4: Abertura e fechamento de cova 30×30×40 cm (MO) | B4: un | C4: ='Custos Unitários'!$D$22 -> 4 | D4: 1 | E4: 1 | F4: 1 | G4: 1 | H4: 1 | I4: 4 | J4: 0
A5: Urna ecológica biodegradável (juta/papelão/sal) | B5: un | C5: ='Custos Unitários'!$D$23 -> 22 | D5: 1 | E5: 1 | F5: 1 | G5: 0 | H5: 0 | I5: 0 | J5: 0
A6: Placa de madeira Ø20 cm tratada (autoclave) + gravação laser | B6: un | C6: ='Custos Unitários'!$D$24 -> 14 | D6: 1 | E6: 1 | F6: 0 | G6: 0 | H6: 0 | I6: 0 | J6: 0
A7: Estaca de fixação da placa de madeira | B7: un | C7: ='Custos Unitários'!$D$25 -> 2 | D7: 1 | E7: 0 | F7: 0 | G7: 0 | H7: 0 | I7: 0 | J7: 0
A8: Varilla metálica galvanizada para placa vertical | B8: un | C8: ='Custos Unitários'!$D$26 -> 7 | D8: 0 | E8: 1 | F8: 0 | G8: 0 | H8: 0 | I8: 0 | J8: 0
A9: Placa de mármore 20×15 cm gravada | B9: un | C9: ='Custos Unitários'!$D$27 -> 38 | D9: 0 | E9: 0 | F9: 1 | G9: 0 | H9: 1 | I9: 0 | J9: 0
A10: Contenedor cilíndrico Ø32×40 cm (polietileno) | B10: un | C10: ='Custos Unitários'!$D$28 -> 32 | D10: 0 | E10: 0 | F10: 0 | G10: 1 | H10: 0 | I10: 4 | J10: 0
A11: Tampa de granito Ø32 cm (corte + polimento) | B11: un | C11: ='Custos Unitários'!$D$29 -> 30 | D11: 0 | E11: 0 | F11: 0 | G11: 1 | H11: 0 | I11: 4 | J11: 0
A12: Placa vidro/policarbonato 15×10 cm gravada + fixação | B12: un | C12: ='Custos Unitários'!$D$30 -> 16 | D12: 0 | E12: 0 | F12: 0 | G12: 1 | H12: 0 | I12: 0 | J12: 0
A13: Cilindro pré-moldado de concreto c/ tampa | B13: un | C13: ='Custos Unitários'!$D$31 -> 38 | D13: 0 | E13: 0 | F13: 0 | G13: 0 | H13: 1 | I13: 0 | J13: 0
A14: Base drenante (gravilla/areia) por cova | B14: un | C14: ='Custos Unitários'!$D$32 -> 2 | D14: 0 | E14: 0 | F14: 1 | G14: 1 | H14: 1 | I14: 4 | J14: 0
A15: Mão de obra de instalação (contenedor/placa) | B15: un | C15: ='Custos Unitários'!$D$33 -> 8 | D15: 0 | E15: 0 | F15: 1 | G15: 1 | H15: 1 | I15: 4 | J15: 0
A16: Planta individual de homenagem | B16: un | C16: ='Custos Unitários'!$D$34 -> 6 | D16: 1 | E16: 1 | F16: 0 | G16: 0 | H16: 0 | I16: 0 | J16: 0
A17: Placa familiar de granito 40×30 cm gravada (Premium) | B17: un | C17: ='Custos Unitários'!$D$35 -> 95 | D17: 0 | E17: 0 | F17: 0 | G17: 0 | H17: 0 | I17: 1 | J17: 0
A18: Paisagismo exclusivo do lote familiar (Premium) | B18: un | C18: ='Custos Unitários'!$D$36 -> 60 | D18: 0 | E18: 0 | F18: 0 | G18: 0 | H18: 0 | I18: 1 | J18: 0
A19: Pétalas/flores para cerimônia | B19: un | C19: ='Custos Unitários'!$D$37 -> 15 | D19: 0 | E19: 0 | F19: 0 | G19: 0 | H19: 0 | I19: 0 | J19: 1
A20: Atendimento cerimonial (2 pessoas × 2 h) | B20: un | C20: ='Custos Unitários'!$D$38 -> 20 | D20: 0 | E20: 0 | F20: 0 | G20: 0 | H20: 0 | I20: 0 | J20: 1
A21: Nome em placa memorial coletiva (aspersão) | B21: un | C21: ='Custos Unitários'!$D$39 -> 10 | D21: 0 | E21: 0 | F21: 0 | G21: 0 | H21: 0 | I21: 0 | J21: 1
A22: Registro, certificado e documentação | B22: un | C22: ='Custos Unitários'!$D$40 -> 3 | D22: 1 | E22: 1 | F22: 1 | G22: 1 | H22: 1 | I22: 1 | J22: 1
A23: CUSTO DIRETO POR UNIDADE VENDIDA | D23: =SUMPRODUCT($C$4:$C$22,D4:D22) -> 51 | E23: =SUMPRODUCT($C$4:$C$22,E4:E22) -> 56 | F23: =SUMPRODUCT($C$4:$C$22,F4:F22) -> 77 | G23: =SUMPRODUCT($C$4:$C$22,G4:G22) -> 95 | H23: =SUMPRODUCT($C$4:$C$22,H4:H22) -> 93 | I23: =SUMPRODUCT($C$4:$C$22,I4:I22) -> 462 | J23: =SUMPRODUCT($C$4:$C$22,J4:J22) -> 48
A25: Quantidades em azul: alterar para refletir a composição final de cada produto. Produtos com contenedor/cilindro não incluem a urna (trazida pelo cliente).
